zotero_local_api/__init__.py
zotero_local_api/client.py
zotero_local_api/exceptions.py
zotero_local_api-0.1.0.dist-info/METADATA
zotero_local_api-0.1.0.dist-info/WHEEL
zotero_local_api-0.1.0.dist-info/licenses/LICENSE
zotero_local_api-0.1.0.dist-info/RECORD
