Metadata-Version: 2.3
Name: zotero-local-api
Version: 0.1.0
Summary: 用于访问本地Zotero服务器API的Python客户端库
Project-URL: Homepage, https://github.com/yourusername/zotero-local-api
Author-email: Your Name <your.email@example.com>
License: MIT License
Classifier: License :: OSI Approved :: MIT License
Classifier: Operating System :: OS Independent
Classifier: Programming Language :: Python :: 3
Requires-Python: >=3.7
Requires-Dist: requests>=2.25.0
